{
    "store_name": "cexce",
    "date": null,
    "items": [
        {
            "name": "878137  18CT EGGS",
            "price": "6.29"
        },
        {
            "name": "77053 GRAPE TOMATO",
            "price": "6.29"
        },
        {
            "name": "404609 ECO HALF PAN",
            "price": "6.49"
        },
        {
            "name": "4.45 E",
            "price": "85.61"
        },
        {
            "name": "Check /Member Prntd",
            "price": "89.13"
        }
    ],
    "total_amount": 85.61
}